route360/__init__.py
route360/config.json
route360/losses.py
route360/outlier_detector.py
route360/route_builder.py
route360/route_finder.py
route360/run_hint3_eval.py
route360/run_sr_hint3_eval.py
route360/unified_llm_caller.py
route360/vector_db.py
route360/data/outliers.csv
route360/data/outliers_v1.csv
route360/data/rostd_eval.csv
route360/data/rostd_eval_full.csv
route360/data/rostd_test.csv
route360/data/rostd_test_full.csv
route360/data/rostd_train.csv
route360/data/rostd_train_full.csv
route_360-0.8.14.dist-info/METADATA
route_360-0.8.14.dist-info/WHEEL
route_360-0.8.14.dist-info/top_level.txt
route_360-0.8.14.dist-info/RECORD
